cipfsuf/__init__.py
cipfsuf-1.3.0.dist-info/METADATA
cipfsuf-1.3.0.dist-info/WHEEL
cipfsuf-1.3.0.dist-info/entry_points.txt
cipfsuf-1.3.0.dist-info/top_level.txt
cipfsuf-1.3.0.dist-info/RECORD
