Metadata-Version: 2.4
Name: cipfsuf
Version: 1.3.0
Author: MurilooPrDev
Requires-Dist: requests
Dynamic: author
Dynamic: requires-dist
